.bzrignore
COPYING
ChangeLog
README.txt
TODO.txt
setup.cfg
setup.py
sflib.wpr
sflib/__init__.py
sflib/aviation.py
sflib/bzrcachedrev.py
sflib/daemonize.py
sflib/delegate.py
sflib/dictclass.py
sflib/finddata.py
sflib/html.py
sflib/lockfile.py
sflib/pathutils.py
sflib/ps.py
sflib/version.py
sflib/visitor.py
sflib.egg-info/PKG-INFO
sflib.egg-info/SOURCES.txt
sflib.egg-info/dependency_links.txt
sflib.egg-info/requires.txt
sflib.egg-info/top_level.txt
sflib.egg-info/zip-safe
sflib/fileconf/__init__.py
sflib/fileconf/config.py
sflib/fileconf/configparser.py
sflib/fileconf/included.conf
sflib/fileconf/testconf.conf
sflib/graph/__init__.py
sflib/queues/__init__.py
sflib/udom/__init__.py
sflib/udom/entity.py
