Metadata-Version: 1.0
Name: sflib
Version: 1.0dev-BZR-r45-panta-elasticworld.org-20091021145839-1oceeh3stpvyl04t
Summary: Foundation library for SoftwareFabrica projects
Home-page: http://cheeseshop.python.org/pypi/sflib/
Author: Marco Pantaleoni
Author-email: m.pantaleoni@softwarefabrica.org
License: GNU GPL v2
Download-URL: http://pypi.python.org/packages/source/s/sflib/sflib-1.0dev-BZR-r45-panta-elasticworld.org-20091021145839-1oceeh3stpvyl04t.tar.gz
Keywords: utilities basic foundation
Platform: UNKNOWN
Classifier: Development Status :: 4 - Beta
Classifier: Intended Audience :: Developers
Classifier: License :: OSI Approved :: GNU General Public License (GPL)
Classifier: Operating System :: OS Independent
Classifier: Programming Language :: Python :: 2.3
Classifier: Topic :: Software Development :: Libraries :: Python Modules
